omniSparql/__init__.py
omniSparql/py.typed
omniSparql/queries.py
omniSparql/sparql.py
omniSparql/utils.py
omniSparql-0.0.3.dist-info/LICENSE
omniSparql-0.0.3.dist-info/METADATA
omniSparql-0.0.3.dist-info/WHEEL
omniSparql-0.0.3.dist-info/top_level.txt
omniSparql-0.0.3.dist-info/RECORD
